purviewcli/__init__.py
purviewcli/cli/__init__.py
purviewcli/cli/account.py
purviewcli/cli/cli.py
purviewcli/cli/entity.py
purviewcli/cli/glossary.py
purviewcli/cli/insight.py
purviewcli/cli/lineage.py
purviewcli/cli/management.py
purviewcli/cli/policystore.py
purviewcli/cli/relationship.py
purviewcli/cli/scan.py
purviewcli/cli/search.py
purviewcli/cli/share.py
purviewcli/cli/types.py
purviewcli/client/__init__.py
purviewcli/client/_account.py
purviewcli/client/_entity.py
purviewcli/client/_glossary.py
purviewcli/client/_insight.py
purviewcli/client/_lineage.py
purviewcli/client/_management.py
purviewcli/client/_policystore.py
purviewcli/client/_relationship.py
purviewcli/client/_scan.py
purviewcli/client/_search.py
purviewcli/client/_share.py
purviewcli/client/_types.py
purviewcli/client/client.py
purviewcli/client/endpoint.py
purviewcli/client/settings.py
purviewcli-0.3.2.dist-info/LICENSE
purviewcli-0.3.2.dist-info/METADATA
purviewcli-0.3.2.dist-info/WHEEL
purviewcli-0.3.2.dist-info/entry_points.txt
purviewcli-0.3.2.dist-info/top_level.txt
purviewcli-0.3.2.dist-info/RECORD
