Metadata-Version: 2.1
Name: purviewcli
Version: 0.3.2
Summary: This package provides a command line interface to Azure Purview's REST API.
Home-page: https://github.com/tayganr/purviewcli
Author: Taygan Rifat
Author-email: contact@taygan.co
License: MIT
Classifier: Programming Language :: Python :: 3
Classifier: License :: OSI Approved :: MIT License
Classifier: Operating System :: OS Independent
License-File: LICENSE
Requires-Dist: docopt
Requires-Dist: requests
Requires-Dist: azure-identity
